pkcs11_cryptography_keys/__init__.py
pkcs11_cryptography_keys/py.typed
pkcs11_cryptography_keys/card_slot/PKCS11_slot.py
pkcs11_cryptography_keys/card_slot/PKCS11_slot_admin.py
pkcs11_cryptography_keys/card_slot/__init__.py
pkcs11_cryptography_keys/card_token/EC_key_definition.py
pkcs11_cryptography_keys/card_token/PKCS11_X509_certificate.py
pkcs11_cryptography_keys/card_token/PKCS11_key_definition.py
pkcs11_cryptography_keys/card_token/PKCS11_keypair.py
pkcs11_cryptography_keys/card_token/PKCS11_token.py
pkcs11_cryptography_keys/card_token/PKCS11_token_admin.py
pkcs11_cryptography_keys/card_token/RSA_key_definition.py
pkcs11_cryptography_keys/card_token/__init__.py
pkcs11_cryptography_keys/keys/__init__.py
pkcs11_cryptography_keys/keys/ec.py
pkcs11_cryptography_keys/keys/eliptic_curve_derive_algorithm.py
pkcs11_cryptography_keys/keys/rsa.py
pkcs11_cryptography_keys/pkcs11_URI/__init__.py
pkcs11_cryptography_keys/pkcs11_URI/definitions.py
pkcs11_cryptography_keys/pkcs11_URI/library_properties_uri.py
pkcs11_cryptography_keys/pkcs11_URI/pkcs11_URI.py
pkcs11_cryptography_keys/pkcs11_URI/slot_properties_uri.py
pkcs11_cryptography_keys/pkcs11_URI/token_properties_uri.py
pkcs11_cryptography_keys/pkcs11_URI/utils.py
pkcs11_cryptography_keys/sessions/PKCS11_admin_session.py
pkcs11_cryptography_keys/sessions/PKCS11_key_session.py
pkcs11_cryptography_keys/sessions/PKCS11_session.py
pkcs11_cryptography_keys/sessions/PKCS11_slot_admin_session.py
pkcs11_cryptography_keys/sessions/PKCS11_slot_session.py
pkcs11_cryptography_keys/sessions/PKCS11_uri_admin_session.py
pkcs11_cryptography_keys/sessions/PKCS11_uri_key_session.py
pkcs11_cryptography_keys/sessions/PKCS11_uri_slot_admin_session.py
pkcs11_cryptography_keys/sessions/PKCS11_uri_slot_session.py
pkcs11_cryptography_keys/sessions/__init__.py
pkcs11_cryptography_keys/utils/__init__.py
pkcs11_cryptography_keys/utils/certificate_properties.py
pkcs11_cryptography_keys/utils/exceptions.py
pkcs11_cryptography_keys-0.0.6.dist-info/licenses/LICENSE
pkcs11_cryptography_keys-0.0.6.dist-info/METADATA
pkcs11_cryptography_keys-0.0.6.dist-info/WHEEL
pkcs11_cryptography_keys-0.0.6.dist-info/top_level.txt
pkcs11_cryptography_keys-0.0.6.dist-info/RECORD
