Metadata-Version: 2.4
Name: PKCS11-cryptography-keys
Version: 0.0.6
Summary: Python chryptography keys implemented on to the PKCS11 interface
Author-email: Miha Šetina <miha.setina@gmail.com>
Maintainer-email: Miha Šetina <miha.setina@gmail.com>
License-Expression: BSD-3-Clause
Project-URL: Homepage, https://github.com/msetina/PKCS11-cryptography-keys
Project-URL: Source Code, https://github.com/msetina/PKCS11-cryptography-keys
Project-URL: Issue Tracker, https://github.com/msetina/PKCS11-cryptography-keys/issues
Keywords: cryptography,pkcs11
Classifier: Development Status :: 3 - Alpha
Classifier: Intended Audience :: Information Technology
Classifier: Intended Audience :: Developers
Classifier: Operating System :: OS Independent
Classifier: Programming Language :: Python :: 3.10
Classifier: Programming Language :: Python :: 3.11
Classifier: Programming Language :: Python :: 3.12
Classifier: Topic :: Security :: Cryptography
Classifier: Topic :: Software Development :: Libraries :: Python Modules
Requires-Python: >=3.10
License-File: LICENSE
Requires-Dist: PyKCS11>=1.5.14
Requires-Dist: cryptography>=44.0.0
Requires-Dist: asn1crypto>=1.5.1
Provides-Extra: testing
Requires-Dist: PKCS11-cryptography-keys; extra == "testing"
Requires-Dist: pytest>=6.1.1; extra == "testing"
Requires-Dist: pytest-cov<6.3,>=4.0; extra == "testing"
Provides-Extra: mypy
Requires-Dist: PKCS11-cryptography-keys; extra == "mypy"
Requires-Dist: types-PyYAML; extra == "mypy"
Dynamic: license-file
